six21/__init__.py
six21/e621.py
six21-0.1.3.dist-info/LICENSE
six21-0.1.3.dist-info/METADATA
six21-0.1.3.dist-info/WHEEL
six21-0.1.3.dist-info/top_level.txt
six21-0.1.3.dist-info/RECORD
