Metadata-Version: 2.1
Name: six21
Version: 0.1.3
Summary: An simple python package for e621
Home-page: https://github.com/Noms1/six21
Author: Noms1
Author-email: kindlefireflame287@gmail.com
Project-URL: Bug Tracker, https://github.com/Noms1/six21/issues
Classifier: Programming Language :: Python :: 3
Classifier: License :: OSI Approved :: MIT License
Classifier: Operating System :: OS Independent
Requires-Python: >=3.6
License-File: LICENSE
